README
setup.py
glassblower/__init__.py
glassblower/glassblower.py
glassblower.egg-info/PKG-INFO
glassblower.egg-info/SOURCES.txt
glassblower.egg-info/dependency_links.txt
glassblower.egg-info/entry_points.txt
glassblower.egg-info/top_level.txt