Metadata-Version: 1.1
Name: glassblower
Version: 0.2.5
Summary: The Best Flask Boilerplate Framework
Home-page: https://github.com/TheCraftsmen/GlassBlower-2
Author: Blas Martin Castro
Author-email: castro.blas.martin@gmail.com
License: BSD
Keywords: Flask Boilerplate Framework Web
Platform: UNKNOWN
Classifier: Development Status :: 3 - Alpha
Classifier: Topic :: Utilities
Classifier: License :: OSI Approved :: BSD License
